flyswot/__init__.py
flyswot/cli.py
flyswot/cli_inference.py
flyswot/config.py
flyswot/console.py
flyswot/core.py
flyswot/inference.py
flyswot/logo.py
flyswot/models.py
flyswot/onnx_inference.py
flyswot/py.typed
flyswot-0.3.15.dist-info/LICENSE.rst
flyswot-0.3.15.dist-info/METADATA
flyswot-0.3.15.dist-info/WHEEL
flyswot-0.3.15.dist-info/entry_points.txt
flyswot-0.3.15.dist-info/RECORD
