Metadata-Version: 2.1
Name: flyswot
Version: 0.3.15
Summary: flyswot
Home-page: https://github.com/davanstrien/flyswot
License: MIT
Author: Daniel van Strien
Author-email: daniel.van-strien@bl.uk
Requires-Python: >=3.8.0,<3.11.0
Classifier: License :: OSI Approved :: MIT License
Classifier: Programming Language :: Python :: 3
Classifier: Programming Language :: Python :: 3.8
Classifier: Programming Language :: Python :: 3.9
Classifier: Programming Language :: Python :: 3.10
Requires-Dist: Pillow (>=8,<11)
Requires-Dist: huggingface-hub (>=0.11.0,<0.17.0)
Requires-Dist: loguru (>=0.6,<0.8)
Requires-Dist: numpy (>=1.20,<2.0)
Requires-Dist: rich (>=10.1,<14.0)
Requires-Dist: toolz (>=0.11.1,<0.13.0)
Requires-Dist: transformers[torch] (>=4.16.2,<5.0.0)
Requires-Dist: typer (>=0.5.0)
Requires-Dist: typing_extensions (>=3.10,<5.0)
Project-URL: Changelog, https://github.com/davanstrien/flyswot/releases
Project-URL: Documentation, https://flyswot.readthedocs.io
Project-URL: Repository, https://github.com/davanstrien/flyswot
